glue/__init__.py
glue/_deps.py
glue/_mpl_backend.py
glue/_plugin_helpers.py
glue/_settings_helpers.py
glue/backends.py
glue/config.py
glue/config_gen.py
glue/conftest.py
glue/default_config.py
glue/logger.py
glue/logo.png
glue/main.py
glue/qglue.py
glue/app/__init__.py
glue/app/qt/__init__.py
glue/app/qt/actions.py
glue/app/qt/application.py
glue/app/qt/application.ui
glue/app/qt/edit_subset_mode_toolbar.py
glue/app/qt/feedback.py
glue/app/qt/keyboard_shortcuts.py
glue/app/qt/layer_tree_widget.py
glue/app/qt/layer_tree_widget.ui
glue/app/qt/mdi_area.py
glue/app/qt/merge.ui
glue/app/qt/metadata.py
glue/app/qt/metadata.ui
glue/app/qt/plugin_manager.py
glue/app/qt/plugin_manager.ui
glue/app/qt/preferences.py
glue/app/qt/preferences.ui
glue/app/qt/report_crash.ui
glue/app/qt/report_feedback.ui
glue/app/qt/save_data.py
glue/app/qt/save_data.ui
glue/app/qt/splash_screen.py
glue/app/qt/terminal.py
glue/app/qt/versions.py
glue/app/qt/versions.ui
glue/app/qt/tests/__init__.py
glue/app/qt/tests/test_actions.py
glue/app/qt/tests/test_application.py
glue/app/qt/tests/test_edit_subset_mode_toolbar.py
glue/app/qt/tests/test_layer_tree_widget.py
glue/app/qt/tests/test_plugin_manager.py
glue/app/qt/tests/test_preferences.py
glue/app/qt/tests/test_save_data.py
glue/app/qt/tests/test_terminal.py
glue/app/tests/__init__.py
glue/core/__init__.py
glue/core/aggregate.py
glue/core/application_base.py
glue/core/autolinking.py
glue/core/callback_property.py
glue/core/command.py
glue/core/component.py
glue/core/component_id.py
glue/core/component_link.py
glue/core/contracts.py
glue/core/coordinate_helpers.py
glue/core/coordinates.py
glue/core/data.py
glue/core/data_collection.py
glue/core/data_combo_helper.py
glue/core/data_derived.py
glue/core/decorators.py
glue/core/edit_subset_mode.py
glue/core/exceptions.py
glue/core/fitters.py
glue/core/fixed_resolution_buffer.py
glue/core/glue_pickle.py
glue/core/hub.py
glue/core/hub_callback_container.py
glue/core/joins.py
glue/core/layer_artist.py
glue_core_for_glue_genes-1.12.3.dist-info/LICENSE
glue_core_for_glue_genes-1.12.3.dist-info/METADATA
glue_core_for_glue_genes-1.12.3.dist-info/WHEEL
glue_core_for_glue_genes-1.12.3.dist-info/entry_points.txt
glue_core_for_glue_genes-1.12.3.dist-info/top_level.txt
glue_core_for_glue_genes-1.12.3.dist-info/RECORD
