Metadata-Version: 2.1
Name: glue-core-for-glue-genes
Version: 1.12.3
Summary: Multidimensional data visualization across files for glue genes
Home-page: http://gluesolutions.io
Author: Thomas Robitaille, Chris Beaumont, Jonathan Foster
Author-email: jfoster@gluesolutions.io
Classifier: Intended Audience :: Science/Research
Classifier: Operating System :: OS Independent
Classifier: Programming Language :: Python
Classifier: Programming Language :: Python :: 3
Classifier: Programming Language :: Python :: 3.8
Classifier: Programming Language :: Python :: 3.9
Classifier: Programming Language :: Python :: 3.10
Classifier: Topic :: Scientific/Engineering :: Visualization
Classifier: License :: OSI Approved :: BSD License
Requires-Python: >=3.8
License-File: LICENSE
Requires-Dist: numpy (>=1.17)
Requires-Dist: matplotlib (>=3.2)
Requires-Dist: scipy (>=1.1)
Requires-Dist: pandas (>=1.2)
Requires-Dist: echo (>=0.6)
Requires-Dist: astropy (>=4.0)
Requires-Dist: setuptools (>=30.3.0)
Requires-Dist: qtpy (>=1.9)
Requires-Dist: ipython (>=4.0)
Requires-Dist: ipykernel (!=5.0.0,!=5.1.0,>=4.0)
Requires-Dist: qtconsole (!=5.4.2,>=4.3)
Requires-Dist: dill (>=0.2)
Requires-Dist: xlrd (>=1.2)
Requires-Dist: openpyxl (>=3.0)
Requires-Dist: mpl-scatter-density (>=0.7)
Requires-Dist: pvextractor (>=0.2)
Requires-Dist: shapely (>=2.0)
Requires-Dist: importlib-metadata (>=3.6) ; python_version < "3.10"
Requires-Dist: h5py (>=2.10) ; python_version < "3.11"
Requires-Dist: importlib-resources (>=1.3) ; python_version < "3.9"
Provides-Extra: all
Requires-Dist: scipy ; extra == 'all'
Requires-Dist: scikit-image ; extra == 'all'
Requires-Dist: PyAVM ; extra == 'all'
Requires-Dist: astrodendro ; extra == 'all'
Requires-Dist: h5py (>=2.10) ; extra == 'all'
Requires-Dist: spectral-cube ; extra == 'all'
Requires-Dist: pillow (!=7.1.0) ; extra == 'all'
Provides-Extra: astronomy
Requires-Dist: PyAVM ; extra == 'astronomy'
Requires-Dist: astrodendro ; extra == 'astronomy'
Requires-Dist: spectral-cube ; extra == 'astronomy'
Provides-Extra: docs
Requires-Dist: sphinx ; extra == 'docs'
Requires-Dist: sphinx-automodapi ; extra == 'docs'
Requires-Dist: sphinxcontrib-spelling ; extra == 'docs'
Requires-Dist: numpydoc ; extra == 'docs'
Requires-Dist: sphinx-rtd-theme ; extra == 'docs'
Provides-Extra: qt
Requires-Dist: PyQt5 (>=5.14) ; extra == 'qt'
Provides-Extra: recommended
Requires-Dist: scikit-image ; extra == 'recommended'
Provides-Extra: test
Requires-Dist: pytest ; extra == 'test'
Requires-Dist: pytest-cov ; extra == 'test'
Requires-Dist: pytest-faulthandler ; extra == 'test'
Requires-Dist: pytest-flake8 ; extra == 'test'
Requires-Dist: objgraph ; extra == 'test'
Requires-Dist: h5py (>=2.10) ; (platform_system == "Linux") and extra == 'test'
